[
    {
      "name": "Nyan Cat",
      "bpm": 500,
      "bitsPerPage": 16,
      "pitchLevel": 0,
      "songNotes": [
        {
          "time": 1920,
          "key": "1Key0"
        },
        {
          "time": 1920,
          "key": "1Key2"
        },
        {
          "time": 2040,
          "key": "1Key3"
        },
        {
          "time": 2160,
          "key": "1Key4"
        },
        {
          "time": 2400,
          "key": "1Key0"
        },
        {
          "time": 2400,
          "key": "1Key7"
        },
        {
          "time": 2640,
          "key": "1Key2"
        },
        {
          "time": 2760,
          "key": "1Key4"
        },
        {
          "time": 2880,
          "key": "1Key0"
        },
        {
          "time": 2880,
          "key": "1Key4"
        },
        {
          "time": 3000,
          "key": "1Key7"
        },
        {
          "time": 3120,
          "key": "1Key8"
        },
        {
          "time": 3240,
          "key": "1Key9"
        },
        {
          "time": 3360,
          "key": "1Key0"
        },
        {
          "time": 3360,
          "key": "1Key8"
        },
        {
          "time": 3480,
          "key": "1Key7"
        },
        {
          "time": 3600,
          "key": "1Key8"
        },
        {
          "time": 3720,
          "key": "1Key9"
        },
        {
          "time": 3840,
          "key": "1Key0"
        },
        {
          "time": 3840,
          "key": "1Key4"
        },
        {
          "time": 3960,
          "key": "1Key2"
        },
        {
          "time": 4080,
          "key": "1Key3"
        },
        {
          "time": 4200,
          "key": "1Key0"
        },
        {
          "time": 4200,
          "key": "1Key4"
        },
        {
          "time": 4440,
          "key": "1Key7"
        },
        {
          "time": 4680,
          "key": "1Key0"
        },
        {
          "time": 4680,
          "key": "1Key8"
        },
        {
          "time": 4800,
          "key": "1Key7"
        },
        {
          "time": 4920,
          "key": "1Key8"
        },
        {
          "time": 5040,
          "key": "1Key9"
        },
        {
          "time": 5160,
          "key": "1Key0"
        },
        {
          "time": 5160,
          "key": "1Key10"
        },
        {
          "time": 5280,
          "key": "1Key9"
        },
        {
          "time": 5400,
          "key": "1Key8"
        },
        {
          "time": 5520,
          "key": "1Key7"
        },
        {
          "time": 5640,
          "key": "1Key3"
        },
        {
          "time": 5640,
          "key": "1Key11"
        },
        {
          "time": 5880,
          "key": "1Key12"
        },
        {
          "time": 6120,
          "key": "1Key4"
        },
        {
          "time": 6120,
          "key": "1Key8"
        },
        {
          "time": 6240,
          "key": "1Key9"
        },
        {
          "time": 6480,
          "key": "1Key7"
        },
        {
          "time": 6600,
          "key": "1Key2"
        },
        {
          "time": 6600,
          "key": "1Key9"
        },
        {
          "time": 6720,
          "key": "1Key8"
        },
        {
          "time": 6840,
          "key": "1Key7"
        },
        {
          "time": 7080,
          "key": "1Key5"
        },
        {
          "time": 7080,
          "key": "1Key7"
        },
        {
          "time": 7320,
          "key": "1Key8"
        },
        {
          "time": 7560,
          "key": "1Key1"
        },
        {
          "time": 7560,
          "key": "1Key9"
        },
        {
          "time": 7800,
          "key": "1Key9"
        },
        {
          "time": 7920,
          "key": "1Key8"
        },
        {
          "time": 8040,
          "key": "1Key4"
        },
        {
          "time": 8040,
          "key": "1Key7"
        },
        {
          "time": 8160,
          "key": "1Key8"
        },
        {
          "time": 8280,
          "key": "1Key9"
        },
        {
          "time": 8400,
          "key": "1Key11"
        },
        {
          "time": 8520,
          "key": "1Key0"
        },
        {
          "time": 8520,
          "key": "1Key12"
        },
        {
          "time": 8640,
          "key": "1Key9"
        },
        {
          "time": 8760,
          "key": "1Key11"
        },
        {
          "time": 8880,
          "key": "1Key8"
        },
        {
          "time": 9000,
          "key": "1Key0"
        },
        {
          "time": 9000,
          "key": "1Key9"
        },
        {
          "time": 9120,
          "key": "1Key7"
        },
        {
          "time": 9240,
          "key": "1Key8"
        },
        {
          "time": 9360,
          "key": "1Key7"
        },
        {
          "time": 9480,
          "key": "1Key3"
        },
        {
          "time": 9480,
          "key": "1Key9"
        },
        {
          "time": 9720,
          "key": "1Key11"
        },
        {
          "time": 9960,
          "key": "1Key4"
        },
        {
          "time": 9960,
          "key": "1Key12"
        },
        {
          "time": 10080,
          "key": "1Key9"
        },
        {
          "time": 10200,
          "key": "1Key11"
        },
        {
          "time": 10320,
          "key": "1Key8"
        },
        {
          "time": 10440,
          "key": "1Key2"
        },
        {
          "time": 10440,
          "key": "1Key9"
        },
        {
          "time": 10560,
          "key": "1Key7"
        },
        {
          "time": 10680,
          "key": "1Key8"
        },
        {
          "time": 10800,
          "key": "1Key9"
        },
        {
          "time": 10920,
          "key": "1Key5"
        },
        {
          "time": 10920,
          "key": "1Key8"
        },
        {
          "time": 11040,
          "key": "1Key7"
        },
        {
          "time": 11160,
          "key": "1Key7"
        },
        {
          "time": 11280,
          "key": "1Key8"
        },
        {
          "time": 11400,
          "key": "1Key1"
        },
        {
          "time": 11400,
          "key": "1Key9"
        },
        {
          "time": 11640,
          "key": "1Key7"
        },
        {
          "time": 11760,
          "key": "1Key8"
        },
        {
          "time": 11880,
          "key": "1Key4"
        },
        {
          "time": 11880,
          "key": "1Key9"
        },
        {
          "time": 12000,
          "key": "1Key11"
        },
        {
          "time": 12120,
          "key": "1Key8"
        },
        {
          "time": 12240,
          "key": "1Key9"
        },
        {
          "time": 12360,
          "key": "1Key0"
        },
        {
          "time": 12360,
          "key": "1Key8"
        },
        {
          "time": 12480,
          "key": "1Key7"
        },
        {
          "time": 12600,
          "key": "1Key8"
        },
        {
          "time": 12840,
          "key": "1Key0"
        },
        {
          "time": 12840,
          "key": "1Key7"
        },
        {
          "time": 13080,
          "key": "1Key8"
        },
        {
          "time": 13320,
          "key": "1Key3"
        },
        {
          "time": 13320,
          "key": "1Key11"
        },
        {
          "time": 13560,
          "key": "1Key12"
        },
        {
          "time": 13800,
          "key": "1Key4"
        },
        {
          "time": 13800,
          "key": "1Key8"
        },
        {
          "time": 13920,
          "key": "1Key9"
        },
        {
          "time": 14160,
          "key": "1Key8"
        },
        {
          "time": 14280,
          "key": "1Key2"
        },
        {
          "time": 14280,
          "key": "1Key9"
        },
        {
          "time": 14400,
          "key": "1Key8"
        },
        {
          "time": 14520,
          "key": "1Key7"
        },
        {
          "time": 14760,
          "key": "1Key5"
        },
        {
          "time": 14760,
          "key": "1Key7"
        },
        {
          "time": 15000,
          "key": "1Key8"
        },
        {
          "time": 15240,
          "key": "1Key1"
        },
        {
          "time": 15240,
          "key": "1Key9"
        },
        {
          "time": 15480,
          "key": "1Key9"
        },
        {
          "time": 15600,
          "key": "1Key8"
        },
        {
          "time": 15720,
          "key": "1Key4"
        },
        {
          "time": 15720,
          "key": "1Key7"
        },
        {
          "time": 15840,
          "key": "1Key8"
        },
        {
          "time": 15960,
          "key": "1Key9"
        },
        {
          "time": 16080,
          "key": "1Key11"
        },
        {
          "time": 16200,
          "key": "1Key0"
        },
        {
          "time": 16200,
          "key": "1Key12"
        },
        {
          "time": 16320,
          "key": "1Key9"
        },
        {
          "time": 16440,
          "key": "1Key11"
        },
        {
          "time": 16560,
          "key": "1Key8"
        },
        {
          "time": 16680,
          "key": "1Key0"
        },
        {
          "time": 16680,
          "key": "1Key9"
        },
        {
          "time": 16800,
          "key": "1Key7"
        },
        {
          "time": 16920,
          "key": "1Key8"
        },
        {
          "time": 17040,
          "key": "1Key7"
        },
        {
          "time": 17160,
          "key": "1Key3"
        },
        {
          "time": 17160,
          "key": "1Key9"
        },
        {
          "time": 17400,
          "key": "1Key11"
        },
        {
          "time": 17640,
          "key": "1Key4"
        },
        {
          "time": 17640,
          "key": "1Key12"
        },
        {
          "time": 17760,
          "key": "1Key9"
        },
        {
          "time": 17880,
          "key": "1Key11"
        },
        {
          "time": 18000,
          "key": "1Key8"
        },
        {
          "time": 18120,
          "key": "1Key2"
        },
        {
          "time": 18120,
          "key": "1Key9"
        },
        {
          "time": 18240,
          "key": "1Key7"
        },
        {
          "time": 18360,
          "key": "1Key8"
        },
        {
          "time": 18480,
          "key": "1Key9"
        },
        {
          "time": 18600,
          "key": "1Key5"
        },
        {
          "time": 18600,
          "key": "1Key8"
        },
        {
          "time": 18720,
          "key": "1Key7"
        },
        {
          "time": 18840,
          "key": "1Key7"
        },
        {
          "time": 18960,
          "key": "1Key8"
        },
        {
          "time": 19080,
          "key": "1Key1"
        },
        {
          "time": 19080,
          "key": "1Key9"
        },
        {
          "time": 19320,
          "key": "1Key7"
        },
        {
          "time": 19440,
          "key": "1Key8"
        },
        {
          "time": 19560,
          "key": "1Key4"
        },
        {
          "time": 19560,
          "key": "1Key9"
        },
        {
          "time": 19680,
          "key": "1Key11"
        },
        {
          "time": 19800,
          "key": "1Key8"
        },
        {
          "time": 19920,
          "key": "1Key9"
        },
        {
          "time": 20040,
          "key": "1Key0"
        },
        {
          "time": 20040,
          "key": "1Key8"
        },
        {
          "time": 20160,
          "key": "1Key7"
        },
        {
          "time": 20280,
          "key": "1Key8"
        },
        {
          "time": 20520,
          "key": "1Key0"
        },
        {
          "time": 20520,
          "key": "1Key7"
        },
        {
          "time": 20760,
          "key": "1Key7"
        },
        {
          "time": 21000,
          "key": "1Key4"
        },
        {
          "time": 21000,
          "key": "1Key7"
        },
        {
          "time": 21240,
          "key": "1Key4"
        },
        {
          "time": 21360,
          "key": "1Key5"
        },
        {
          "time": 21480,
          "key": "1Key7"
        },
        {
          "time": 21720,
          "key": "1Key4"
        },
        {
          "time": 21840,
          "key": "1Key5"
        },
        {
          "time": 21960,
          "key": "1Key2"
        },
        {
          "time": 21960,
          "key": "1Key7"
        },
        {
          "time": 22080,
          "key": "1Key8"
        },
        {
          "time": 22200,
          "key": "1Key9"
        },
        {
          "time": 22320,
          "key": "1Key7"
        },
        {
          "time": 22440,
          "key": "1Key5"
        },
        {
          "time": 22440,
          "key": "1Key10"
        },
        {
          "time": 22560,
          "key": "1Key9"
        },
        {
          "time": 22680,
          "key": "1Key10"
        },
        {
          "time": 22800,
          "key": "1Key11"
        },
        {
          "time": 22920,
          "key": "1Key1"
        },
        {
          "time": 22920,
          "key": "1Key7"
        },
        {
          "time": 23160,
          "key": "1Key7"
        },
        {
          "time": 23400,
          "key": "1Key4"
        },
        {
          "time": 23520,
          "key": "1Key5"
        },
        {
          "time": 23640,
          "key": "1Key7"
        },
        {
          "time": 23760,
          "key": "1Key3"
        },
        {
          "time": 23880,
          "key": "1Key0"
        },
        {
          "time": 23880,
          "key": "1Key10"
        },
        {
          "time": 24000,
          "key": "1Key9"
        },
        {
          "time": 24120,
          "key": "1Key8"
        },
        {
          "time": 24240,
          "key": "1Key7"
        },
        {
          "time": 24360,
          "key": "1Key0"
        },
        {
          "time": 24360,
          "key": "1Key4"
        },
        {
          "time": 24480,
          "key": "1Key2"
        },
        {
          "time": 24600,
          "key": "1Key3"
        },
        {
          "time": 24720,
          "key": "1Key4"
        },
        {
          "time": 24840,
          "key": "1Key3"
        },
        {
          "time": 24840,
          "key": "1Key7"
        },
        {
          "time": 25080,
          "key": "1Key4"
        },
        {
          "time": 25200,
          "key": "1Key5"
        },
        {
          "time": 25320,
          "key": "1Key4"
        },
        {
          "time": 25320,
          "key": "1Key7"
        },
        {
          "time": 25560,
          "key": "1Key4"
        },
        {
          "time": 25680,
          "key": "1Key5"
        },
        {
          "time": 25800,
          "key": "1Key2"
        },
        {
          "time": 25800,
          "key": "1Key7"
        },
        {
          "time": 25920,
          "key": "1Key7"
        },
        {
          "time": 26040,
          "key": "1Key8"
        },
        {
          "time": 26160,
          "key": "1Key9"
        },
        {
          "time": 26280,
          "key": "1Key5"
        },
        {
          "time": 26280,
          "key": "1Key7"
        },
        {
          "time": 26400,
          "key": "1Key4"
        },
        {
          "time": 26520,
          "key": "1Key5"
        },
        {
          "time": 26640,
          "key": "1Key4"
        },
        {
          "time": 26760,
          "key": "1Key1"
        },
        {
          "time": 26760,
          "key": "1Key7"
        },
        {
          "time": 27000,
          "key": "1Key7"
        },
        {
          "time": 27120,
          "key": "1Key6"
        },
        {
          "time": 27240,
          "key": "1Key7"
        },
        {
          "time": 27360,
          "key": "1Key4"
        },
        {
          "time": 27480,
          "key": "1Key5"
        },
        {
          "time": 27600,
          "key": "1Key7"
        },
        {
          "time": 27720,
          "key": "1Key0"
        },
        {
          "time": 27720,
          "key": "1Key10"
        },
        {
          "time": 27840,
          "key": "1Key9"
        },
        {
          "time": 27960,
          "key": "1Key10"
        },
        {
          "time": 28080,
          "key": "1Key11"
        },
        {
          "time": 28200,
          "key": "1Key0"
        },
        {
          "time": 28200,
          "key": "1Key7"
        },
        {
          "time": 28440,
          "key": "1Key6"
        },
        {
          "time": 28680,
          "key": "1Key4"
        },
        {
          "time": 28680,
          "key": "1Key7"
        },
        {
          "time": 28920,
          "key": "1Key4"
        },
        {
          "time": 29040,
          "key": "1Key5"
        },
        {
          "time": 29160,
          "key": "1Key4"
        },
        {
          "time": 29160,
          "key": "1Key7"
        },
        {
          "time": 29400,
          "key": "1Key4"
        },
        {
          "time": 29520,
          "key": "1Key5"
        },
        {
          "time": 29640,
          "key": "1Key2"
        },
        {
          "time": 29640,
          "key": "1Key7"
        },
        {
          "time": 29760,
          "key": "1Key8"
        },
        {
          "time": 29880,
          "key": "1Key9"
        },
        {
          "time": 30000,
          "key": "1Key7"
        },
        {
          "time": 30120,
          "key": "1Key5"
        },
        {
          "time": 30120,
          "key": "1Key10"
        },
        {
          "time": 30240,
          "key": "1Key9"
        },
        {
          "time": 30360,
          "key": "1Key10"
        },
        {
          "time": 30480,
          "key": "1Key11"
        },
        {
          "time": 30600,
          "key": "1Key1"
        },
        {
          "time": 30600,
          "key": "1Key7"
        },
        {
          "time": 30840,
          "key": "1Key7"
        },
        {
          "time": 31080,
          "key": "1Key4"
        },
        {
          "time": 31200,
          "key": "1Key5"
        },
        {
          "time": 31320,
          "key": "1Key7"
        },
        {
          "time": 31440,
          "key": "1Key4"
        },
        {
          "time": 31560,
          "key": "1Key0"
        },
        {
          "time": 31560,
          "key": "1Key10"
        },
        {
          "time": 31680,
          "key": "1Key9"
        },
        {
          "time": 31800,
          "key": "1Key8"
        },
        {
          "time": 31920,
          "key": "1Key7"
        },
        {
          "time": 32040,
          "key": "1Key0"
        },
        {
          "time": 32040,
          "key": "1Key4"
        },
        {
          "time": 32160,
          "key": "1Key2"
        },
        {
          "time": 32280,
          "key": "1Key3"
        },
        {
          "time": 32400,
          "key": "1Key4"
        },
        {
          "time": 32520,
          "key": "1Key3"
        },
        {
          "time": 32520,
          "key": "1Key7"
        },
        {
          "time": 32760,
          "key": "1Key4"
        },
        {
          "time": 32880,
          "key": "1Key5"
        },
        {
          "time": 33000,
          "key": "1Key4"
        },
        {
          "time": 33000,
          "key": "1Key7"
        },
        {
          "time": 33240,
          "key": "1Key4"
        },
        {
          "time": 33360,
          "key": "1Key5"
        },
        {
          "time": 33480,
          "key": "1Key2"
        },
        {
          "time": 33480,
          "key": "1Key7"
        },
        {
          "time": 33600,
          "key": "1Key7"
        },
        {
          "time": 33720,
          "key": "1Key8"
        },
        {
          "time": 33840,
          "key": "1Key9"
        },
        {
          "time": 33960,
          "key": "1Key5"
        },
        {
          "time": 33960,
          "key": "1Key7"
        },
        {
          "time": 34080,
          "key": "1Key4"
        },
        {
          "time": 34200,
          "key": "1Key5"
        },
        {
          "time": 34320,
          "key": "1Key4"
        },
        {
          "time": 34440,
          "key": "1Key1"
        },
        {
          "time": 34440,
          "key": "1Key7"
        },
        {
          "time": 34680,
          "key": "1Key7"
        },
        {
          "time": 34920,
          "key": "1Key4"
        },
        {
          "time": 35040,
          "key": "1Key5"
        },
        {
          "time": 35160,
          "key": "1Key7"
        },
        {
          "time": 35280,
          "key": "1Key4"
        },
        {
          "time": 35400,
          "key": "1Key0"
        },
        {
          "time": 35400,
          "key": "1Key10"
        },
        {
          "time": 35520,
          "key": "1Key9"
        },
        {
          "time": 35640,
          "key": "1Key8"
        },
        {
          "time": 35760,
          "key": "1Key7"
        },
        {
          "time": 35880,
          "key": "1Key0"
        },
        {
          "time": 35880,
          "key": "1Key4"
        },
        {
          "time": 35880,
          "key": "1Key7"
        }
      ]
    }
  ]